grokcore/startup/README.rst
grokcore/startup/__init__.py
grokcore/startup/debug.py
grokcore/startup/startup.py
grokcore/startup/tests/__init__.py
grokcore/startup/tests/test_grokcorestartup.py
grokcore_startup-5.0.dist-info/licenses/LICENSE.txt
grokcore_startup-5.0.dist-info/METADATA
grokcore_startup-5.0.dist-info/WHEEL
grokcore_startup-5.0.dist-info/entry_points.txt
grokcore_startup-5.0.dist-info/top_level.txt
grokcore_startup-5.0.dist-info/RECORD
