Metadata-Version: 2.4
Name: grokcore.startup
Version: 5.0
Summary: Paster support for Grok projects.
Home-page: https://github.com/zopefoundation/grokcore.startup
Author: Grok Team
Author-email: zope-dev@zope.dev
License: ZPL
Keywords: zope zope3 grok grokproject WSGI Paste paster
Classifier: Environment :: Web Environment
Classifier: Framework :: Zope :: 3
Classifier: Intended Audience :: Developers
Classifier: License :: OSI Approved :: Zope Public License
Classifier: Programming Language :: Python
Classifier: Programming Language :: Python :: 3
Classifier: Programming Language :: Python :: 3.9
Classifier: Programming Language :: Python :: 3.10
Classifier: Programming Language :: Python :: 3.11
Classifier: Programming Language :: Python :: 3.12
Classifier: Programming Language :: Python :: 3.13
Classifier: Programming Language :: Python :: Implementation
Classifier: Programming Language :: Python :: Implementation :: CPython
Classifier: Programming Language :: Python :: Implementation :: PyPy
Requires-Python: >=3.9
License-File: LICENSE.txt
Requires-Dist: setuptools
Requires-Dist: zope.app.debug
Requires-Dist: zope.app.wsgi
Requires-Dist: zope.component
Requires-Dist: zope.dottedname
Requires-Dist: zope.publisher
Provides-Extra: test
Requires-Dist: zope.app.appsetup; extra == "test"
Requires-Dist: zope.component; extra == "test"
Requires-Dist: zope.interface; extra == "test"
Requires-Dist: zope.security; extra == "test"
Requires-Dist: zope.securitypolicy; extra == "test"
Requires-Dist: zope.testing; extra == "test"
Requires-Dist: zope.testrunner>=6.4; extra == "test"
Provides-Extra: debug
Requires-Dist: IPython>=8; extra == "debug"
Dynamic: author
Dynamic: author-email
Dynamic: classifier
Dynamic: description
Dynamic: home-page
Dynamic: keywords
Dynamic: license
Dynamic: license-file
Dynamic: provides-extra
Dynamic: requires-dist
Dynamic: requires-python
Dynamic: summary
